<?xml version="1.0" encoding="utf-8"?>
<IncrementalBankBuild Version="6" Flags="601859981">
	<Platform GUID="{2B7D36AE-163E-4655-ADC8-20B178554FFF}">
		<Banks>
			<Language ID="393239870">
				<File Name="Init" Hash="2315450116" Timestamp="1578760951"/>
				<File Name="New_SoundBank" Hash="3311224394" Timestamp="1578849940"/>
			</Language>
		</Banks>
		<XMLInfo>
			<Language ID="-1">
				<File Name="" Hash="3975495422" Timestamp="1578849940"/>
			</Language>
		</XMLInfo>
	</Platform>
</IncrementalBankBuild>
